pathdf/__init__.py
pathdf/pathdf.py
pathdf-0.2.0.dist-info/LICENSE
pathdf-0.2.0.dist-info/METADATA
pathdf-0.2.0.dist-info/WHEEL
pathdf-0.2.0.dist-info/entry_points.txt
pathdf-0.2.0.dist-info/top_level.txt
pathdf-0.2.0.dist-info/RECORD
