Metadata-Version: 2.1
Name: pathdf
Version: 0.2.0
Summary: A package to export file paths to various formats like csv or dataframe
Home-page: https://github.com/MJBioInfo/pathdf
Author: Dr.Majeed Jamakhani
Author-email: mjbioinfo@gmail.com
Classifier: Programming Language :: Python :: 3
Classifier: License :: OSI Approved :: MIT License
Classifier: Operating System :: OS Independent
Requires-Python: >=3.6
License-File: LICENSE
Requires-Dist: pandas
Requires-Dist: openpyxl
